aiohomekit/__init__.py
aiohomekit/__main__.py
aiohomekit/characteristic_cache.py
aiohomekit/const.py
aiohomekit/controller/__init__.py
aiohomekit/controller/abstract.py
aiohomekit/controller/ble/__init__.py
aiohomekit/controller/ble/bleak.py
aiohomekit/controller/ble/client.py
aiohomekit/controller/ble/connection.py
aiohomekit/controller/ble/const.py
aiohomekit/controller/ble/controller.py
aiohomekit/controller/ble/discovery.py
aiohomekit/controller/ble/key.py
aiohomekit/controller/ble/manufacturer_data.py
aiohomekit/controller/ble/pairing.py
aiohomekit/controller/ble/structs.py
aiohomekit/controller/ble/values.py
aiohomekit/controller/coap/__init__.py
aiohomekit/controller/coap/connection.py
aiohomekit/controller/coap/controller.py
aiohomekit/controller/coap/discovery.py
aiohomekit/controller/coap/pairing.py
aiohomekit/controller/coap/pdu.py
aiohomekit/controller/coap/structs.py
aiohomekit/controller/controller.py
aiohomekit/controller/ip/__init__.py
aiohomekit/controller/ip/connection.py
aiohomekit/controller/ip/controller.py
aiohomekit/controller/ip/discovery.py
aiohomekit/controller/ip/pairing.py
aiohomekit/crypto/__init__.py
aiohomekit/crypto/chacha20poly1305.py
aiohomekit/crypto/hkdf.py
aiohomekit/crypto/srp.py
aiohomekit/enum.py
aiohomekit/exceptions.py
aiohomekit/hkjson.py
aiohomekit/http/__init__.py
aiohomekit/http/response.py
aiohomekit/meshcop.py
aiohomekit/model/__init__.py
aiohomekit/model/categories.py
aiohomekit/model/characteristics/__init__.py
aiohomekit/model/characteristics/characteristic.py
aiohomekit/model/characteristics/characteristic_formats.py
aiohomekit/model/characteristics/characteristic_types.py
aiohomekit/model/characteristics/const.py
aiohomekit/model/characteristics/data.py
aiohomekit/model/characteristics/permissions.py
aiohomekit/model/characteristics/structs.py
aiohomekit/model/characteristics/types.py
aiohomekit/model/characteristics/units.py
aiohomekit/model/entity_map.py
aiohomekit/model/feature_flags.py
aiohomekit-3.2.19.dist-info/METADATA
aiohomekit-3.2.19.dist-info/WHEEL
aiohomekit-3.2.19.dist-info/entry_points.txt
aiohomekit-3.2.19.dist-info/licenses/LICENSE.md
aiohomekit-3.2.19.dist-info/RECORD
