Metadata-Version: 2.4
Name: aiohomekit
Version: 3.2.19
Summary: An asyncio HomeKit client
License-Expression: Apache-2.0
License-File: LICENSE.md
Keywords: HomeKit,home,automation
Author: John Carr
Author-email: john.carr@unrouted.co.uk
Requires-Python: >=3.10
Classifier: Intended Audience :: Developers
Classifier: Intended Audience :: End Users/Desktop
Classifier: Programming Language :: Python :: 3
Classifier: Programming Language :: Python :: 3.10
Classifier: Programming Language :: Python :: 3.11
Classifier: Programming Language :: Python :: 3.12
Classifier: Programming Language :: Python :: 3.13
Classifier: Topic :: Home Automation
Requires-Dist: aiocoap (>=0.4.5)
Requires-Dist: aiohappyeyeballs (>=2.3.0)
Requires-Dist: async-interrupt (>=1.1.1)
Requires-Dist: async-timeout (>=4.0.2) ; python_version < "3.11"
Requires-Dist: bleak (>=0.22.0)
Requires-Dist: bleak-retry-connector (>=2.9.0)
Requires-Dist: chacha20poly1305 (>=0.0.3,<0.0.4)
Requires-Dist: chacha20poly1305-reuseable (>=0.12.1)
Requires-Dist: commentjson (>=0.9.0,<0.10.0)
Requires-Dist: cryptography (>=2.9.2)
Requires-Dist: orjson (>=3.7.8)
Requires-Dist: zeroconf (>=0.132.2)
Project-URL: Homepage, https://github.com/Jc2k/aiohomekit
Project-URL: Repository, https://github.com/Jc2k/aiohomekit
